QCandyUi/CandyWindow.py
QCandyUi/Titlebar.py
QCandyUi/WindowWithTitleBar.py
QCandyUi/__init__.py
QCandyUi/qss_getter.py
QCandyUi/resourse_cfg.py
QCandyUi/simple_qss.py
QCandyUi/candyUi/theme.json
QCandyUi/candyUi/blue/checkbox_down.png
QCandyUi/candyUi/blue/checkbox_hoverCheck.png
QCandyUi/candyUi/blue/checkbox_hoverUncheck.png
QCandyUi/candyUi/blue/checkbox_normal.png
QCandyUi/candyUi/blue/close.png
QCandyUi/candyUi/blue/closehover.png
QCandyUi/candyUi/blue/closepress.png
QCandyUi/candyUi/blue/down_arrow.png
QCandyUi/candyUi/blue/maxsize.png
QCandyUi/candyUi/blue/maxsizehover.png
QCandyUi/candyUi/blue/maxsizepress.png
QCandyUi/candyUi/blue/minsize.png
QCandyUi/candyUi/blue/minsizehover.png
QCandyUi/candyUi/blue/minsizepress.png
QCandyUi/candyUi/blue/radio_down.png
QCandyUi/candyUi/blue/radio_hoverCheck.png
QCandyUi/candyUi/blue/radio_hoverUncheck.png
QCandyUi/candyUi/blue/radio_normal.png
QCandyUi/candyUi/blue/resize.png
QCandyUi/candyUi/blue/resizehover.png
QCandyUi/candyUi/blue/resizepress.png
QCandyUi/candyUi/blueDeep/checkbox_down.png
QCandyUi/candyUi/blueDeep/checkbox_hoverCheck.png
QCandyUi/candyUi/blueDeep/checkbox_hoverUncheck.png
QCandyUi/candyUi/blueDeep/checkbox_normal.png
QCandyUi/candyUi/blueDeep/close.png
QCandyUi/candyUi/blueDeep/closehover.png
QCandyUi/candyUi/blueDeep/closepress.png
QCandyUi/candyUi/blueDeep/down_arrow.png
QCandyUi/candyUi/blueDeep/maxsize.png
QCandyUi/candyUi/blueDeep/maxsizehover.png
QCandyUi/candyUi/blueDeep/maxsizepress.png
QCandyUi/candyUi/blueDeep/minsize.png
QCandyUi/candyUi/blueDeep/minsizehover.png
QCandyUi/candyUi/blueDeep/minsizepress.png
QCandyUi/candyUi/blueDeep/radio_down.png
QCandyUi/candyUi/blueDeep/radio_hoverCheck.png
QCandyUi/candyUi/blueDeep/radio_hoverUncheck.png
QCandyUi/candyUi/blueDeep/radio_normal.png
QCandyUi/candyUi/blueDeep/resize.png
QCandyUi/candyUi/blueDeep/resizehover.png
QCandyUi/candyUi/blueDeep/resizepress.png
QCandyUi/candyUi/blueGreen/checkbox_down.png
QCandyUi-0.15.dist-info/METADATA
QCandyUi-0.15.dist-info/WHEEL
QCandyUi-0.15.dist-info/top_level.txt
QCandyUi-0.15.dist-info/RECORD
