Metadata-Version: 2.1
Name: QCandyUi
Version: 0.15
Summary: quick beautify your pyQt5 app
Home-page: https://github.com/shuoGG1239/QCandyUi
Author: shuoGG
Author-email: 328893769@qq.com
License: UNKNOWN
Keywords: python pyQt ui
Platform: UNKNOWN
Requires-Dist: pywin32
